{"customer_id": "C1", "basket": [{"product_id": "P36", "price": 1006}], "date_of_purchase": "2019-01-16 07:11:00"}
{"customer_id": "C3", "basket": [{"product_id": "P03", "price": 982}, {"product_id": "P12", "price": 947}], "date_of_purchase": "2019-01-16 09:47:00"}
{"customer_id": "C4", "basket": [{"product_id": "P61", "price": 611}, {"product_id": "P64", "price": 467}, {"product_id": "P63", "price": 1432}], "date_of_purchase": "2019-01-16 11:44:00"}
{"customer_id": "C7", "basket": [{"product_id": "P42", "price": 1911}], "date_of_purchase": "2019-01-16 11:02:00"}
{"customer_id": "C12", "basket": [{"product_id": "P09", "price": 1381}, {"product_id": "P04", "price": 331}], "date_of_purchase": "2019-01-16 18:53:00"}
{"customer_id": "C24", "basket": [{"product_id": "P63", "price": 217}, {"product_id": "P62", "price": 1836}], "date_of_purchase": "2019-01-16 08:12:00"}
{"customer_id": "C28", "basket": [{"product_id": "P05", "price": 1290}], "date_of_purchase": "2019-01-16 05:14:00"}
{"customer_id": "C30", "basket": [{"product_id": "P04", "price": 66}, {"product_id": "P01", "price": 690}, {"product_id": "P12", "price": 1717}], "date_of_purchase": "2019-01-16 19:20:00"}
{"customer_id": "C38", "basket": [{"product_id": "P44", "price": 1058}], "date_of_purchase": "2019-01-16 12:51:00"}
{"customer_id": "C45", "basket": [{"product_id": "P38", "price": 1196}], "date_of_purchase": "2019-01-16 19:51:00"}
{"customer_id": "C46", "basket": [{"product_id": "P40", "price": 51}], "date_of_purchase": "2019-01-16 08:42:00"}
{"customer_id": "C47", "basket": [{"product_id": "P02", "price": 1474}], "date_of_purchase": "2019-01-16 20:00:00"}
{"customer_id": "C48", "basket": [{"product_id": "P10", "price": 160}, {"product_id": "P04", "price": 814}, {"product_id": "P02", "price": 453}], "date_of_purchase": "2019-01-16 08:30:00"}
{"customer_id": "C65", "basket": [{"product_id": "P09", "price": 751}], "date_of_purchase": "2019-01-16 12:34:00"}
{"customer_id": "C74", "basket": [{"product_id": "P27", "price": 1290}, {"product_id": "P28", "price": 1034}, {"product_id": "P22", "price": 1401}], "date_of_purchase": "2019-01-16 05:47:00"}
{"customer_id": "C80", "basket": [{"product_id": "P64", "price": 1706}, {"product_id": "P61", "price": 880}], "date_of_purchase": "2019-01-16 18:25:00"}
{"customer_id": "C83", "basket": [{"product_id": "P11", "price": 1761}], "date_of_purchase": "2019-01-16 09:41:00"}
{"customer_id": "C88", "basket": [{"product_id": "P64", "price": 300}], "date_of_purchase": "2019-01-16 04:25:00"}
{"customer_id": "C90", "basket": [{"product_id": "P40", "price": 505}, {"product_id": "P36", "price": 550}], "date_of_purchase": "2019-01-16 06:09:00"}
{"customer_id": "C93", "basket": [{"product_id": "P63", "price": 423}, {"product_id": "P61", "price": 542}], "date_of_purchase": "2019-01-16 16:47:00"}
{"customer_id": "C98", "basket": [{"product_id": "P35", "price": 600}, {"product_id": "P39", "price": 768}], "date_of_purchase": "2019-01-16 05:06:00"}
{"customer_id": "C103", "basket": [{"product_id": "P16", "price": 134}], "date_of_purchase": "2019-01-16 13:08:00"}
{"customer_id": "C109", "basket": [{"product_id": "P35", "price": 720}, {"product_id": "P38", "price": 1147}], "date_of_purchase": "2019-01-16 17:25:00"}
{"customer_id": "C118", "basket": [{"product_id": "P29", "price": 728}], "date_of_purchase": "2019-01-16 19:57:00"}
{"customer_id": "C120", "basket": [{"product_id": "P34", "price": 341}], "date_of_purchase": "2019-01-16 07:06:00"}
{"customer_id": "C128", "basket": [{"product_id": "P38", "price": 1099}, {"product_id": "P35", "price": 1647}], "date_of_purchase": "2019-01-16 10:04:00"}
